{"11":[11,"Happy Around!",1,"sugoroku_enemy_normal_1","LiveStartEnemy0011",1.33],"21":[21,"Peaky P-key",2,"sugoroku_enemy_normal_2","LiveStartEnemy0021",1.33],"31":[31,"Photon Maiden",3,"sugoroku_enemy_normal_3","LiveStartEnemy0031",1.33],"41":[41,"Merm4id",4,"sugoroku_enemy_normal_4","LiveStartEnemy0041",1.33],"51":[51,"燐舞曲",5,"sugoroku_enemy_normal_5","LiveStartEnemy0051",1.33],"61":[61,"Lyrical Lily",6,"sugoroku_enemy_normal_6","LiveStartEnemy0061",1.33],"81":[81,"UniChØrd",8,"sugoroku_enemy_normal_8","LiveStartEnemy0081",1.33],"91":[91,"Abyssmare",9,"sugoroku_enemy_normal_9","LiveStartEnemy0091",1.33],"1001":[1001,"駆け出しDJユニット",999,"sugoroku_enemy_normal_999","LiveStartEnemy0999",1.33],"1002":[1002,"半人前DJユニット",999,"sugoroku_enemy_normal_999","LiveStartEnemy0999",1.33],"1003":[1003,"一人前DJユニット",999,"sugoroku_enemy_normal_999","LiveStartEnemy0999",1.33],"1004":[1004,"熟練DJユニット",999,"sugoroku_enemy_normal_999","LiveStartEnemy0999",1.33],"1005":[1005,"強豪DJユニット",999,"sugoroku_enemy_normal_999","LiveStartEnemy0999",1.33]}